steiner_tree/__init__.py
steiner_tree/bank/__init__.py
steiner_tree/bank/solver.py
steiner_tree/bank/struct.py
steiner_tree/disconnected.py
steiner_tree-1.2.2.dist-info/LICENSE
steiner_tree-1.2.2.dist-info/METADATA
steiner_tree-1.2.2.dist-info/WHEEL
steiner_tree-1.2.2.dist-info/RECORD
